<?xml version="1.0" encoding="UTF-8"?>
<!DOCTYPE plist PUBLIC "-//Apple//DTD PLIST 1.0//EN" "http://www.apple.com/DTDs/PropertyList-1.0.dtd"/>

<plist version="1.0">
    <dict>
        <key>ROOT</key>
        <array>
            <dict>
                <key>id</key>
                <string>106</string>
            </dict>
            <dict>
                <key>id</key>
                <string>121</string>
            </dict>
            <dict>
                <key>id</key>
                <string>342</string>
            </dict>
            <dict>
                <key>id</key>
                <string>442</string>
            </dict>
            <dict>
                <key>id</key>
                <string>1043</string>
            </dict>
            <dict>
                <key>id</key>
                <string>1051</string>
            </dict>
            <dict>
                <key>id</key>
                <string>1187</string>
            </dict>
            <dict>
                <key>id</key>
                <string>1449</string>
            </dict>
            <dict>
                <key>id</key>
                <string>1593</string>
            </dict>
            <dict>
                <key>id</key>
                <string>1602</string>
            </dict>
            <dict>
                <key>id</key>
                <string>1694</string>
            </dict>
            <dict>
                <key>id</key>
                <string>1714</string>
            </dict>
            <dict>
                <key>id</key>
                <string>1772</string>
            </dict>
            <dict>
                <key>id</key>
                <string>1778</string>
            </dict>
            <dict>
                <key>id</key>
                <string>1837</string>
            </dict>
            <dict>
                <key>id</key>
                <string>1843</string>
            </dict>
            <dict>
                <key>id</key>
                <string>1846</string>
            </dict>
            <dict>
                <key>id</key>
                <string>1851</string>
            </dict>
            <dict>
                <key>id</key>
                <string>1859</string>
            </dict>
            <dict>
                <key>id</key>
                <string>1874</string>
            </dict>
            <dict>
                <key>id</key>
                <string>1880</string>
            </dict>
            <dict>
                <key>id</key>
                <string>1883</string>
            </dict>
            <dict>
                <key>id</key>
                <string>1886</string>
            </dict>
            <dict>
                <key>id</key>
                <string>1889</string>
            </dict>
            <dict>
                <key>id</key>
                <string>1896</string>
            </dict>
            <dict>
                <key>id</key>
                <string>1899</string>
            </dict>
            <dict>
                <key>id</key>
                <string>1933</string>
            </dict>
            <dict>
                <key>id</key>
                <string>1936</string>
            </dict>
            <dict>
                <key>id</key>
                <string>1955</string>
            </dict>
            <dict>
                <key>id</key>
                <string>1969</string>
            </dict>
            <dict>
                <key>id</key>
                <string>1982</string>
            </dict>
            <dict>
                <key>id</key>
                <string>2019</string>
            </dict>
            <dict>
                <key>id</key>
                <string>2023</string>
            </dict>
            <dict>
                <key>id</key>
                <string>2084</string>
            </dict>
            <dict>
                <key>id</key>
                <string>2104</string>
            </dict>
            <dict>
                <key>id</key>
                <string>2118</string>
            </dict>
            <dict>
                <key>id</key>
                <string>2119</string>
            </dict>
            <dict>
                <key>id</key>
                <string>2120</string>
            </dict>
            <dict>
                <key>id</key>
                <string>2121</string>
            </dict>
            <dict>
                <key>id</key>
                <string>2122</string>
            </dict>
            <dict>
                <key>id</key>
                <string>2123</string>
            </dict>
            <dict>
                <key>id</key>
                <string>2201</string>
            </dict>
            <dict>
                <key>id</key>
                <string>2254</string>
            </dict>
            <dict>
                <key>id</key>
                <string>2329</string>
            </dict>
            <dict>
                <key>id</key>
                <string>2330</string>
            </dict>
            <dict>
                <key>id</key>
                <string>2331</string>
            </dict>
            <dict>
                <key>id</key>
                <string>2332</string>
            </dict>
            <dict>
                <key>id</key>
                <string>2333</string>
            </dict>
            <dict>
                <key>id</key>
                <string>2334</string>
            </dict>
            <dict>
                <key>id</key>
                <string>2335</string>
            </dict>
            <dict>
                <key>id</key>
                <string>2336</string>
            </dict>
            <dict>
                <key>id</key>
                <string>2347</string>
            </dict>
            <dict>
                <key>id</key>
                <string>2413</string>
            </dict>
            <dict>
                <key>id</key>
                <string>2419</string>
            </dict>
            <dict>
                <key>id</key>
                <string>2431</string>
            </dict>
            <dict>
                <key>id</key>
                <string>2437</string>
            </dict>
            <dict>
                <key>id</key>
                <string>2443</string>
            </dict>
            <dict>
                <key>id</key>
                <string>2539</string>
            </dict>
            <dict>
                <key>id</key>
                <string>2543</string>
            </dict>
            <dict>
                <key>id</key>
                <string>2570</string>
            </dict>
            <dict>
                <key>id</key>
                <string>2571</string>
            </dict>
            <dict>
                <key>id</key>
                <string>2572</string>
            </dict>
            <dict>
                <key>id</key>
                <string>2573</string>
            </dict>
            <dict>
                <key>id</key>
                <string>2574</string>
            </dict>
            <dict>
                <key>id</key>
                <string>2575</string>
            </dict>
            <dict>
                <key>id</key>
                <string>2576</string>
            </dict>
            <dict>
                <key>id</key>
                <string>2577</string>
            </dict>
            <dict>
                <key>id</key>
                <string>2578</string>
            </dict>
            <dict>
                <key>id</key>
                <string>2579</string>
            </dict>
            <dict>
                <key>id</key>
                <string>2580</string>
            </dict>
            <dict>
                <key>id</key>
                <string>2581</string>
            </dict>
            <dict>
                <key>id</key>
                <string>2582</string>
            </dict>
            <dict>
                <key>id</key>
                <string>2583</string>
            </dict>
            <dict>
                <key>id</key>
                <string>2584</string>
            </dict>
            <dict>
                <key>id</key>
                <string>2585</string>
            </dict>
            <dict>
                <key>id</key>
                <string>2586</string>
            </dict>
            <dict>
                <key>id</key>
                <string>2613</string>
            </dict>
            <dict>
                <key>id</key>
                <string>2624</string>
            </dict>
            <dict>
                <key>id</key>
                <string>2727</string>
            </dict>
            <dict>
                <key>id</key>
                <string>2741</string>
            </dict>
            <dict>
                <key>id</key>
                <string>2749</string>
            </dict>
            <dict>
                <key>id</key>
                <string>2759</string>
            </dict>
            <dict>
                <key>id</key>
                <string>2765</string>
            </dict>
            <dict>
                <key>id</key>
                <string>2771</string>
            </dict>
            <dict>
                <key>id</key>
                <string>2775</string>
            </dict>
            <dict>
                <key>id</key>
                <string>2811</string>
            </dict>
            <dict>
                <key>id</key>
                <string>2817</string>
            </dict>
            <dict>
                <key>id</key>
                <string>2829</string>
            </dict>
            <dict>
                <key>id</key>
                <string>2835</string>
            </dict>
            <dict>
                <key>id</key>
                <string>3011</string>
            </dict>
            <dict>
                <key>id</key>
                <string>3032</string>
            </dict>
            <dict>
                <key>id</key>
                <string>3144</string>
            </dict>
            <dict>
                <key>id</key>
                <string>3155</string>
            </dict>
            <dict>
                <key>id</key>
                <string>3174</string>
            </dict>
            <dict>
                <key>id</key>
                <string>3202</string>
            </dict>
            <dict>
                <key>id</key>
                <string>3306</string>
            </dict>
            <dict>
                <key>id</key>
                <string>3327</string>
            </dict>
            <dict>
                <key>id</key>
                <string>3422</string>
            </dict>
            <dict>
                <key>id</key>
                <string>3493</string>
            </dict>
            <dict>
                <key>id</key>
                <string>3583</string>
            </dict>
            <dict>
                <key>id</key>
                <string>3656</string>
            </dict>
            <dict>
                <key>id</key>
                <string>3665</string>
            </dict>
            <dict>
                <key>id</key>
                <string>3751</string>
            </dict>
            <dict>
                <key>id</key>
                <string>3760</string>
            </dict>
            <dict>
                <key>id</key>
                <string>3769</string>
            </dict>
            <dict>
                <key>id</key>
                <string>3778</string>
            </dict>
            <dict>
                <key>id</key>
                <string>3786</string>
            </dict>
            <dict>
                <key>id</key>
                <string>3790</string>
            </dict>
            <dict>
                <key>id</key>
                <string>3796</string>
            </dict>
            <dict>
                <key>id</key>
                <string>3800</string>
            </dict>
            <dict>
                <key>id</key>
                <string>3804</string>
            </dict>
            <dict>
                <key>id</key>
                <string>3808</string>
            </dict>
            <dict>
                <key>id</key>
                <string>3815</string>
            </dict>
        </array>
    </dict>
</plist>
